{
  "kolay": [
    { "kelime": "Elma", "yasakli_kelimeler": ["Kırmızı", "Meyve", "Ağaç", "Yeşil", "Tatlı"] },
    { "kelime": "Gözlük", "yasakli_kelimeler": ["Cam", "Görmek", "Lens", "Çerçeve", "Güneş"] },
    { "kelime": "Köpek", "yasakli_kelimeler": ["Havlamak", "Evcil", "Sadık", "Kulübe", "Tas"] },
    { "kelime": "Telefon", "yasakli_kelimeler": ["Arama", "Mesaj", "Mobil", "Ses", "Şarj"] },
    { "kelime": "Uçak", "yasakli_kelimeler": ["Kanat", "Havaalanı", "Pilot", "Gök", "Uçuş"] },
    { "kelime": "Kedi", "yasakli_kelimeler": ["Miyav", "Tüy", "Evcil", "Tasma", "Fare"] },
    { "kelime": "Araba", "yasakli_kelimeler": ["Tekerlek", "Motor", "Direksiyon", "Yol", "Sürmek"] },
    { "kelime": "Saat", "yasakli_kelimeler": ["Zaman", "Dakika", "Kol", "Göstergesi", "Çalar"] },
    { "kelime": "Televizyon", "yasakli_kelimeler": ["Ekran", "Kanal", "Film", "İzlemek", "Dizi"] },
    { "kelime": "Çikolata", "yasakli_kelimeler": ["Tatlı", "Kakao", "Şeker", "Bitter", "Sütlü"] },
    { "kelime": "Bisiklet", "yasakli_kelimeler": ["Pedal", "Tekerlek", "Sürmek", "Kask", "Yol"] },
    { "kelime": "Balon", "yasakli_kelimeler": ["Helyum", "Uçmak", "Hava", "Patlamak", "Renkli"] },
    { "kelime": "Kalem", "yasakli_kelimeler": ["Yazı", "Mürekkep", "Kağıt", "Defter", "Okul"] },
    { "kelime": "Masa", "yasakli_kelimeler": ["Ahşap", "Mobilya", "Sandalye", "Oturmak", "Ofis"] },
    { "kelime": "Kapı", "yasakli_kelimeler": ["Giriş", "Kilitlemek", "Açmak", "Oda", "Anahtar"] },
    { "kelime": "Lamba", "yasakli_kelimeler": ["Işık", "Ampul", "Gece", "Aydınlatma", "Elektrik"] },
    { "kelime": "Karpuz", "yasakli_kelimeler": ["Meyve", "Kırmızı", "Tatlı", "Çekirdek", "Büyük"] },
    { "kelime": "Şemsiye", "yasakli_kelimeler": ["Yağmur", "Güneş", "Koruma", "Sap", "Açmak"] },
    { "kelime": "Deniz", "yasakli_kelimeler": ["Su", "Kum", "Kıyı", "Mavi", "Dalga"] },
    { "kelime": "Spor", "yasakli_kelimeler": ["Oyun", "Takım", "Yarış", "Hareket", "Sağlık"] },
    { "kelime": "Güneş", "yasakli_kelimeler": ["Sıcak", "Yaz", "Işık", "Sarı", "Gökyüzü"] },
    { "kelime": "Ay", "yasakli_kelimeler": ["Gece", "Gökyüzü", "Yıldız", "Parlak", "Yuvarlak"] },
    { "kelime": "Bulut", "yasakli_kelimeler": ["Beyaz", "Gökyüzü", "Yağmur", "Hava", "Pamuk"] },
    { "kelime": "Ayakkabı", "yasakli_kelimeler": ["Ayak", "Giymek", "Bağcık", "Deri", "Spor"] },
    { "kelime": "Top", "yasakli_kelimeler": ["Yuvarlak", "Oyun", "Atmak", "Tutmak", "Oyuncak"] },
    { "kelime": "Çorap", "yasakli_kelimeler": ["Ayak", "Giymek", "Pamuk", "Yün", "Çift"] },
    { "kelime": "Diş", "yasakli_kelimeler": ["Ağız", "Fırçalamak", "Beyaz", "Sağlık", "Dişçi"] },
    { "kelime": "Bardak", "yasakli_kelimeler": ["Su", "İçmek", "Cam", "Plastik", "Kupa"] },
    { "kelime": "Yıldız", "yasakli_kelimeler": ["Gece", "Gökyüzü", "Parlak", "Uzay", "Işık"] },
    { "kelime": "Kuş", "yasakli_kelimeler": ["Uçmak", "Kanat", "Tüy", "Gökyüzü", "Şarkı"] },
    { "kelime": "Balık", "yasakli_kelimeler": ["Su", "Deniz", "Yüzmek", "Pul", "Yüzgeç"] },
    { "kelime": "Kelebek", "yasakli_kelimeler": ["Uçmak", "Kanat", "Renkli", "Çiçek", "Böcek"] },
    { "kelime": "Ağaç", "yasakli_kelimeler": ["Yaprak", "Dal", "Orman", "Kök", "Doğa"] },
    { "kelime": "Çiçek", "yasakli_kelimeler": ["Renkli", "Kokulu", "Bahçe", "Bitki", "Doğa"] },
    { "kelime": "Ev", "yasakli_kelimeler": ["Oda", "Çatı", "Kapı", "Pencere", "Yaşamak"] }

  ],
  "orta": [
    { "kelime": "Satranç", "yasakli_kelimeler": ["Şah", "Mat", "Hamle", "Oyun", "Taş"] },
    { "kelime": "Deniz Feneri", "yasakli_kelimeler": ["Kıyı", "Işık", "Gece", "Gemiler", "Tepe"] },
    { "kelime": "Sihirbaz", "yasakli_kelimeler": ["Gösteri", "İllüzyon", "Şapka", "Kart", "Numara"] },
    { "kelime": "Pusula", "yasakli_kelimeler": ["Yön", "Kuzey", "İğne", "Manyetik", "Kutuplar"] },
    { "kelime": "Mikroskop", "yasakli_kelimeler": ["Bakteri", "Lens", "Bilim", "Küçük", "Görmek"] },
    { "kelime": "Dürbün", "yasakli_kelimeler": ["Göz", "Yakınlaştırmak", "Gözlem", "Mercek", "Uzak"] },
    { "kelime": "Keman", "yasakli_kelimeler": ["Müzik", "Yay", "Nota", "Orkestra", "Ahşap"] },
    { "kelime": "Kale", "yasakli_kelimeler": ["Taş", "Sur", "Ortaçağ", "Kral", "Savunma"] },
    { "kelime": "Fosil", "yasakli_kelimeler": ["Dinozor", "Tarih", "Taş", "Kazı", "Keşif"] },
    { "kelime": "Astronot", "yasakli_kelimeler": ["Uzay", "Roket", "Yerçekimi", "Gezegen", "NASA"] },
    { "kelime": "Dinozor", "yasakli_kelimeler": ["Tarih", "Fosil", "Jurassic", "Sürüngen", "Dev"] },
    { "kelime": "Harita", "yasakli_kelimeler": ["Coğrafya", "Yön", "Yer", "Şehir", "Kıta"] },
    { "kelime": "Robot", "yasakli_kelimeler": ["Makine", "Yapay Zeka", "Otomatik", "Metal", "Teknoloji"] },
    { "kelime": "Teleskop", "yasakli_kelimeler": ["Uzay", "Gözlem", "Lens", "Yıldız", "Astronomi"] },
    { "kelime": "Müzik", "yasakli_kelimeler": ["Nota", "Şarkı", "Ses", "Enstrüman", "Ritim"] },
    { "kelime": "Volkan", "yasakli_kelimeler": ["Yanardağ", "Lav", "Patlama", "Kül", "Doğa"] },
    { "kelime": "Rüya", "yasakli_kelimeler": ["Uyku", "Gece", "Hayal", "Kabus", "Düşünce"] },
    { "kelime": "Gizem", "yasakli_kelimeler": ["Sır", "Bilinmeyen", "Çözmek", "Merak", "Soru"] },
    { "kelime": "Macera", "yasakli_kelimeler": ["Gezi", "Keşif", "Heyecan", "Tehlike", "Yolculuk"] },
    { "kelime": "İlham", "yasakli_kelimeler": ["Yaratıcılık", "Fikir", "Motivasyon", "Düşünce", "Sanat"] },
    { "kelime": "Hazine", "yasakli_kelimeler": ["Altın", "Para", "Değerli", "Gizli", "Arama"] },
    { "kelime": "Festival", "yasakli_kelimeler": ["Müzik", "Eğlence", "Kutlama", "Dans", "Kalabalık"] },
    { "kelime": "Doğa", "yasakli_kelimeler": ["Ağaç", "Orman", "Hayvan", "Bitki", "Yeşil"] },
    { "kelime": "Fotoğraf", "yasakli_kelimeler": ["Kamera", "Anı", "Görüntü", "Çekmek", "Albüm"] },
    { "kelime": "Heykel", "yasakli_kelimeler": ["Sanat", "Taş", "Mermer", "Oymak", "Sergi"] },
    { "kelime": "Tiyatro", "yasakli_kelimeler": ["Oyun", "Sahne", "Oyuncu", "Seyirci", "Perde"] },
    { "kelime": "Roman", "yasakli_kelimeler": ["Kitap", "Okumak", "Yazar", "Hikaye", "Karakter"] },
    { "kelime": "Şiir", "yasakli_kelimeler": ["Dize", "Yazmak", "Şair", "Duygu", "Anlam"] },
    { "kelime": "Mutfak", "yasakli_kelimeler": ["Yemek", "Pişirmek", "Ocak", "Tencere", "Buzdolabı"] },
    { "kelime": "Banyo", "yasakli_kelimeler": ["Su", "Duş", "Havlu", "Sabun", "Temizlik"] },
    { "kelime": "Yatak", "yasakli_kelimeler": ["Uyku", "Oda", "Yastık", "Battaniye", "Dinlenmek"] },
    { "kelime": "Bahçe", "yasakli_kelimeler": ["Çiçek", "Ağaç", "Bitki", "Toprak", "Yeşil"] },
    { "kelime": "Sokak", "yasakli_kelimeler": ["Yol", "Araba", "Ev", "İnsan", "Yürümek"] },
    { "kelime": "Şehir", "yasakli_kelimeler": ["Bina", "İnsan", "Kalabalık", "Sokak", "Yaşam"] },
    { "kelime": "Ülke", "yasakli_kelimeler": ["Bayrak", "Harita", "Sınır", "Millet", "Vatan"] },
    { "kelime": "Gezegen", "yasakli_kelimeler": ["Dünya", "Uzay", "Yıldız", "Güneş", "Ay"] },
    { "kelime": "Hayvan", "yasakli_kelimeler": ["Kedi", "Köpek", "Kuş", "Balık", "Doğa"] },
    { "kelime": "Bitki", "yasakli_kelimeler": ["Ağaç", "Çiçek", "Yaprak", "Kök", "Doğa"] },
    { "kelime": "Algı", "yasakli_kelimeler": ["Duygu", "Düşünce", "Gerçeklik", "Yorum", "Anlam"] },
    { "kelime": "Bilinç", "yasakli_kelimeler": ["Farkındalık", "Düşünce", "Zihin", "Benlik", "Varoluş"] },
    { "kelime": "Dil", "yasakli_kelimeler": ["Konuşmak", "Anlatmak", "İletişim", "Kelime", "Anlam"] },
    { "kelime": "Kültür", "yasakli_kelimeler": ["Gelenek", "Görenek", "Sanat", "Tarih", "Toplum"] },
    { "kelime": "Zaman", "yasakli_kelimeler": ["Geçmiş", "Gelecek", "Şimdi", "Saat", "Süre"] },
    { "kelime": "Mekan", "yasakli_kelimeler": ["Yer", "Konum", "Alan", "Sınır", "Mesafe"] },
    { "kelime": "Gerçeklik", "yasakli_kelimeler": ["Doğru", "Varoluş", "Hayal", "Algı", "Olgu"] },
    { "kelime": "Hayal", "yasakli_kelimeler": ["Düş", "Rüya", "Fantezi", "Gerçek", "Düşünce"] },
    { "kelime": "Benlik", "yasakli_kelimeler": ["Kimlik", "Kişilik", "Farkındalık", "Bilinç", "Varoluş"] },
    { "kelime": "Değer", "yasakli_kelimeler": ["Önem", "Anlam", "İlke", "Ahlak", "Kültür"] }

  ],
  "zor": [
    { "kelime": "Paralel Evren", "yasakli_kelimeler": ["Boyut", "Alternatif", "Fizik", "Gerçeklik", "Teori"] },
    { "kelime": "Kuantum Fiziği", "yasakli_kelimeler": ["Atom", "Dalga", "Parçacık", "Elektron", "Enerji"] },
    { "kelime": "Dijital Sanat", "yasakli_kelimeler": ["Bilgisayar", "Çizim", "Grafik", "Ekran", "Tasarım"] },
    { "kelime": "Mitoloji", "yasakli_kelimeler": ["Tanrı", "Efsane", "Hikaye", "Antik", "Kahraman"] },
    { "kelime": "Jeotermal Enerji", "yasakli_kelimeler": ["Yeraltı", "Sıcak", "Doğa", "Volkan", "Elektrik"] },
    { "kelime": "Fraktal", "yasakli_kelimeler": ["Geometri", "Matematik", "Karmaşık", "Düzen", "Doğa"] },
    { "kelime": "Astrofizik", "yasakli_kelimeler": ["Uzay", "Gezegen", "Yıldız", "Kara Delik", "Evren"] },
    { "kelime": "Tersine Mühendislik", "yasakli_kelimeler": ["Analiz", "Kod", "Donanım", "Teknoloji", "Çözüm"] },
    { "kelime": "Nanoteknoloji", "yasakli_kelimeler": ["Atom", "Molekül", "Mikroskopik", "Malzeme", "Bilim"] },
    { "kelime": "Blokzincir", "yasakli_kelimeler": ["Kripto", "Para", "Veri", "Güvenlik", "Şifreleme"] },
    { "kelime": "Yapay Zeka", "yasakli_kelimeler": ["Robot", "Makine", "Öğrenme", "Algoritma", "Teknoloji"] },
    { "kelime": "Biyoteknoloji", "yasakli_kelimeler": ["Gen", "Hücre", "Organizma", "Biyoloji", "Tıp"] },
    { "kelime": "Holografi", "yasakli_kelimeler": ["3D", "Görüntü", "Lazer", "Işık", "Projeksiyon"] },
    { "kelime": "Entropi", "yasakli_kelimeler": ["Düzensizlik", "Termodinamik", "Enerji", "Sistem", "Fizik"] },
    { "kelime": "Simbiyoz", "yasakli_kelimeler": ["İlişki", "Organizma", "Doğa", "Yaşam", "Birlikte"] },
    { "kelime": "Arkeoloji", "yasakli_kelimeler": ["Kazı", "Tarih", "Kalıntı", "Eski", "Geçmiş"] },
    { "kelime": "Paleontoloji", "yasakli_kelimeler": ["Fosil", "Dinozor", "Tarih Öncesi", "Hayvan", "Bitki"] },
    { "kelime": "Antropoloji", "yasakli_kelimeler": ["İnsan", "Kültür", "Toplum", "Evrim", "Tarih"] },
    { "kelime": "Nostalji", "yasakli_kelimeler": ["Geçmiş", "Anı", "Duygu", "Özlem", "Hatıra"] },
    { "kelime": "Empati", "yasakli_kelimeler": ["Anlamak", "Duygu", "Başkası", "Hissetmek", "Paylaşmak"] },
    { "kelime": "Manipülasyon", "yasakli_kelimeler": ["Kontrol", "Etki", "Yönlendirme", "Gizli", "Kullanmak"] },
    { "kelime": "Prokrastinasyon", "yasakli_kelimeler": ["Ertelemek", "Yapmak", "İş", "Görev", "Zaman"] },
    { "kelime": "Serendipite", "yasakli_kelimeler": ["Tesadüf", "Şans", "Keşif", "Beklenmedik", "Bulmak"] },
    { "kelime": "Minimalizm", "yasakli_kelimeler": ["Az", "Sade", "Basit", "Eşya", "Yaşam"] },
    { "kelime": "Felsefe", "yasakli_kelimeler": ["Düşünce", "Varoluş", "Bilgi", "Soru", "Anlam"] },
    { "kelime": "Umut", "yasakli_kelimeler": ["İyimserlik", "Gelecek", "Beklenti", "İnanç", "Hayal"] },
    { "kelime": "Özgürlük", "yasakli_kelimeler": ["Bağımsızlık", "Hak", "Sınır", "Kısıtlama", "İrade"] },
    { "kelime": "Stokastik", "yasakli_kelimeler": ["Rastgele", "Olasılık", "İstatistik", "Matematik", "Değişken"] },
    { "kelime": "Epistemoloji", "yasakli_kelimeler": ["Bilgi", "Felsefe", "Doğru", "İnanç", "Gerçek"] },
    { "kelime": "Ontoloji", "yasakli_kelimeler": ["Varoluş", "Gerçeklik", "Felsefe", "Varlık", "Doğa"] },
    { "kelime": "Paradoks", "yasakli_kelimeler": ["Çelişki", "Mantık", "Düşünce", "Sorun", "Çözüm"] },
    { "kelime": "Sinerji", "yasakli_kelimeler": ["Birlikte", "İşbirliği", "Etki", "Güç", "Toplam"] }
  ]
}
